testsumm/__init__.py
testsumm/modulo.py
testsumm-0.2.4.dist-info/METADATA
testsumm-0.2.4.dist-info/WHEEL
testsumm-0.2.4.dist-info/top_level.txt
testsumm-0.2.4.dist-info/RECORD
