Metadata-Version: 2.1
Name: testsumm
Version: 0.2.4
Summary: library ML
Author: Luciano M
Author-email: luciano.munoz1@udea.edu.co
License: MIT
Requires-Python: >=3.10.12
Requires-Dist: numpy
